semal/__init__.py
semal/preprocessing.py
semal/utils.py
semal-0.0.1.dist-info/LICENSE
semal-0.0.1.dist-info/METADATA
semal-0.0.1.dist-info/WHEEL
semal-0.0.1.dist-info/top_level.txt
semal-0.0.1.dist-info/RECORD
