Metadata-Version: 2.1
Name: semal
Version: 0.0.1
Summary: Tools for deserializing sklearn objects
Author: Tibor Mach
License: Mozilla Public License Version 2.0
Project-URL: Homepage, https://github.com/tibor-mach/semal
Keywords: deserialization,scikit-learn,machine learning
Requires-Python: >=3.9
License-File: LICENSE
Requires-Dist: scikit-learn (>=1.2)
Provides-Extra: dev
Requires-Dist: semal[test] ; extra == 'dev'
Requires-Dist: jupyterlab (==3.5) ; extra == 'dev'
Requires-Dist: seaborn ; extra == 'dev'
Requires-Dist: furo ; extra == 'dev'
Requires-Dist: nbsphinx ; extra == 'dev'
Requires-Dist: numpydoc ; extra == 'dev'
Requires-Dist: sphinx ; extra == 'dev'
Requires-Dist: sphinx-copybutton ; extra == 'dev'
Requires-Dist: sphinx-inline-tabs ; extra == 'dev'
Requires-Dist: sphinx-jsonschema ; extra == 'dev'
Requires-Dist: sphinx-design ; extra == 'dev'
Provides-Extra: test
Requires-Dist: pytest (==7.2) ; extra == 'test'
Requires-Dist: pytest-clarity (==1.0.1) ; extra == 'test'
Requires-Dist: black (==23.1.0) ; extra == 'test'
Requires-Dist: pre-commit ; extra == 'test'
Requires-Dist: docformatter[tomli] ; extra == 'test'
